chopper/__init__.py
chopper/extractor.py
chopper/mixins.py
chopper/test_extractor.py
chopper/tests.py
chopper/css/__init__.py
chopper/css/extractor.py
chopper/css/parser.py
chopper/css/rules.py
chopper/css/translator.py
chopper/html/__init__.py
chopper/html/extractor.py
chopper-0.6.0.dist-info/AUTHORS
chopper-0.6.0.dist-info/LICENSE
chopper-0.6.0.dist-info/METADATA
chopper-0.6.0.dist-info/WHEEL
chopper-0.6.0.dist-info/top_level.txt
chopper-0.6.0.dist-info/RECORD
