Metadata-Version: 2.1
Name: chopper
Version: 0.6.0
Summary: Lib to extract html elements by preserving ancestors and cleaning CSS
Home-page: https://github.com/jurismarches/chopper
Author: Jurismarches
Author-email: contact@octopusmind.info
License: UNKNOWN
Platform: UNKNOWN
Classifier: Development Status :: 5 - Production/Stable
Classifier: License :: OSI Approved :: MIT License
Classifier: Intended Audience :: Developers
Classifier: Programming Language :: Python
Classifier: Programming Language :: Python :: 3.8
Classifier: Programming Language :: Python :: 3.9
Classifier: Programming Language :: Python :: 3.10
Classifier: Programming Language :: Python :: 3.11
License-File: LICENSE
License-File: AUTHORS
Requires-Dist: cssselect (>=1.2.0)
Requires-Dist: lxml (>=4.9.1)
Requires-Dist: tinycss (==0.4)
